qdrive/__init__.py
qdrive/pytest.ini
qdrive/scopes.py
qdrive/__pycache__/__init__.cpython-311.pyc
qdrive/dataset/__init__.py
qdrive/dataset/dataset.py
qdrive/dataset/file_manager.py
qdrive/dataset/search.py
qdrive/dataset/files/HDF5.py
qdrive/dataset/files/__init__.py
qdrive/dataset/files/file.py
qdrive/dataset/files/file_mgr_single.py
qdrive/dataset/files/json.py
qdrive/dataset/files/numpy.py
qdrive/dataset/files/utility.py
qdrive/demo/__init__.py
qdrive/demo/station.py
qdrive/measurement/__init__.py
qdrive/measurement/data_collector.py
qdrive/measurement/data_collector_var.py
qdrive/measurement/measurement.py
qdrive/measurement/sweeps.py
qdrive/measurement/HDF5_collector/__init__.py
qdrive/measurement/HDF5_collector/ds_cache.py
qdrive/measurement/HDF5_collector/h5_cache.py
qdrive/measurement/HDF5_collector/h5_dependency_builder.py
qdrive/measurement/HDF5_collector/h5_writer.py
qdrive/measurement/HDF5_collector/h5_writer_container.py
qdrive/measurement/__pycache__/__init__.cpython-311.pyc
qdrive/measurement/__pycache__/data_collector_var.cpython-311.pyc
qdrive/measurement/old/core_tools/sweeps/scans.py
qdrive/measurement/old/core_tools/sweeps/sweeps.py
qdrive/measurement/utility/__init__.py
qdrive/measurement/utility/irregular_ds_conversion.py
qdrive/measurement/utility/__pycache__/__init__.cpython-311.pyc
qdrive/measurement/utility/__pycache__/data_prepocessor.cpython-311.pyc
qdrive/utility/__init__.py
qdrive/utility/copy.py
qdrive/utility/qcodes_metadata.py
qdrive/utility/uploads.py
qdrive/utility/__pycache__/__init__.cpython-311.pyc
qdrive/utility/__pycache__/folders.cpython-311.pyc
qdrive-0.2.54.dist-info/licenses/LICENCE
test/__init__.py
test/conftest.py
test/datasets/__init__.py
test/datasets/dataset_tags.py
test/datasets/datasets_file_access.py
test/offline_access/conftest.py
test/offline_access/datasets.py
test/offline_access/files.py
test/offline_access/scopes.py
test/utility/test_copy.py
test/utility/test_folder_upload.py
test/utility/test_qcodes_metadata.py
qdrive-0.2.54.dist-info/METADATA
qdrive-0.2.54.dist-info/WHEEL
qdrive-0.2.54.dist-info/top_level.txt
qdrive-0.2.54.dist-info/zip-safe
qdrive-0.2.54.dist-info/RECORD
