Metadata-Version: 2.4
Name: qdrive
Version: 0.2.54
Summary: Qdrive dataset library
Author: QDrive team
Requires-Python: >=3.7
License-File: LICENCE
Requires-Dist: PyYAML>=6.0.0
Requires-Dist: platformdirs>=4.0.0
Requires-Dist: numpy>=1.16.0
Requires-Dist: xarray<=0.20.2,>=0.15.0; python_version < "3.8"
Requires-Dist: xarray>=0.15.0; python_version >= "3.8"
Requires-Dist: h5py<=3.8.0,>=3.0.0; python_version < "3.8"
Requires-Dist: h5py>=3.0.0; python_version >= "3.8"
Requires-Dist: qcodes>=0.31.0
Requires-Dist: etiket_client>=0.2.54
Dynamic: license-file
